Metadata-Version: 1.0
Name: uvsnap
Version: 2.0.0
Summary: UVSnap: UniFi Video Command Line Client
Home-page: https://github.com/ampledata/uvsnap
Author: Greg Albrecht
Author-email: oss@undef.net
License: Copyright 2017 Greg Albrecht
